blaidd-0.1.0.dist-info/METADATA
blaidd-0.1.0.dist-info/WHEEL
blaidd-0.1.0.dist-info/licenses/LICENSE
blaidd/__init__.py
blaidd/_rblaidd.abi3.so
blaidd/centroids.py
blaidd/graph.py
blaidd-0.1.0.dist-info/RECORD
