Metadata-Version: 2.4
Name: blaidd
Version: 0.1.0
Classifier: Development Status :: 4 - Beta
Classifier: License :: OSI Approved :: MIT License
Classifier: Intended Audience :: Developers
Classifier: Intended Audience :: Science/Research
Classifier: Programming Language :: Python :: 3
Classifier: Programming Language :: Python :: 3.13
Classifier: Programming Language :: Python :: Implementation :: CPython
Classifier: Programming Language :: Python
Classifier: Programming Language :: Rust
Classifier: Topic :: Scientific/Engineering
Classifier: Topic :: Scientific/Engineering :: Visualization
Classifier: Topic :: Utilities
Requires-Dist: narwhals>=2.1.1
Requires-Dist: numpy>=2.3.2
Requires-Dist: polars>=1.31.0
License-File: LICENSE
Summary: Helper to color scatterplots with labels
Requires-Python: >=3.11
